{
  "project_info": {
    "project_number": "399331187738",
    "project_id": "vanokhi-web",
    "storage_bucket": "vanokhi-web.firebasestorage.app"
  },
  "client": [
    {
      "client_info": {
        "mobilesdk_app_id": "1:399331187738:android:ebfeafbdb1c9c8276405a3",
        "android_client_info": {
          "package_name": "com.vanokhi.app"
        }
      },
      "oauth_client": [
        {
          "client_id": "399331187738-1228o0imtblip9n3ja173u6f1gfklagc.apps.googleusercontent.com",
          "client_type": 1,
          "android_info": {
            "package_name": "com.vanokhi.app",
            "certificate_hash": "17b8bd746626524b140821beede99340f8e0c7ef"
          }
        },
        {
          "client_id": "399331187738-eflpp9q55b7u250g7kudg85j9j4f801o.apps.googleusercontent.com",
          "client_type": 3
        }
      ],
      "api_key": [
        {
          "current_key": "AIzaSyAFa5slNPq1p2vKk_KCrFAAsjIutmvTVFk"
        }
      ],
      "services": {
        "appinvite_service": {
          "other_platform_oauth_client": [
            {
              "client_id": "399331187738-eflpp9q55b7u250g7kudg85j9j4f801o.apps.googleusercontent.com",
              "client_type": 3
            }
          ]
        }
      }
    }
  ],
  "configuration_version": "1"
}